haruzira_sdk-2.1.0.dist-info/DESCRIPTION.rst
haruzira_sdk-2.1.0.dist-info/METADATA
haruzira_sdk-2.1.0.dist-info/RECORD
haruzira_sdk-2.1.0.dist-info/WHEEL
haruzira_sdk-2.1.0.dist-info/metadata.json
haruzira_sdk-2.1.0.dist-info/top_level.txt
haruzirasdk/__init__.py
haruzirasdk/haruzira_message.py
haruzirasdk/hz_client_tcp_communication.py
haruzirasdk/hz_encryption.py
haruzirasdk/hz_speech_recognition_command_info.py
haruzirasdk/hz_trace.py
haruzirasdk/msg_ack_send_speech_data.py
haruzirasdk/msg_ack_send_speech_recognition_command.py
haruzirasdk/msg_ack_start_comm.py
haruzirasdk/msg_notify_complete_speech.py
haruzirasdk/msg_notify_end_comm.py
haruzirasdk/msg_notify_stop_comm.py
haruzirasdk/msg_req_start_comm.py
haruzirasdk/msg_send_speech_data.py
haruzirasdk/msg_send_speech_recognition_command.py
