Metadata-Version: 2.0
Name: haruzira-sdk
Version: 2.1.0
Summary: This package is a SDK for tcp communication with Haruzira(Windows UWP APP).
Home-page: http://haruzirasdke.wpblog.jp/
Author: Symmetry Soft
Author-email: git@symmetry-soft.com
License: MIT
Requires-Dist: numpy
Requires-Dist: pycrypto
